btmesh
