Metadata-Version: 1.1
Name: PyBtMesh
Version: 0.1.3
Summary: Python module for bluetooth mesh
Home-page: https://github.com/samuelli2019/PyBtMesh
Author: samuelli2019
Author-email: lijyigac@gmail.com
License: UNKNOWN
Platform: UNKNOWN
Classifier: Development Status :: 2 - Pre-Alpha
Classifier: Intended Audience :: Developers
Classifier: Topic :: Software Development :: Libraries :: Python Modules
Requires: bitstring
Requires: cryptography
